sympymod/__init__.py
sympymod/calculus.py
sympymod/equation.py
sympymod/pick.py
sympymod/utils.py
sympymod-0.0.3.dist-info/LICENSE
sympymod-0.0.3.dist-info/METADATA
sympymod-0.0.3.dist-info/WHEEL
sympymod-0.0.3.dist-info/top_level.txt
sympymod-0.0.3.dist-info/RECORD
